Workbook

Sheet Year by Year
A1: Year | B1: Era | C1: Status | D1: Event / Episode | E1: Category | F1: Geography | G1: What Happened | H1: Severity (0-5)
A2: 800 | B2: Pre-market (800-1299) | C2: Quiet | D2: Charlemagne's silver denier standard consolidated | E2: Market milestone | F2: Carolingian Empire | G2: The reformed silver penny became the money of account for Western Europe for the next five centuries. Western Europe had no gold coinage of its own from this point until 1252 - a measure of how far behind Baghdad and Constantinople it had fallen. | H2: 0
A3: 801 | B3: Pre-market (800-1299) | C3: Quiet | D3: No major recorded crisis, default or scandal | E3: None | F3: - | G3: No episode of significant scale in the surviving record for this year. Coverage in this period is fragmentary everywhere and near-absent for much of Europe; silence is very weak evidence. | H3: 0
A4: 802 | B4: Pre-market (800-1299) | C4: Quiet | D4: No major recorded crisis, default or scandal | E4: None | F4: - | G4: No episode of significant scale in the surviving record for this year. Coverage in this period is fragmentary everywhere and near-absent for much of Europe; silence is very weak evidence. | H4: 0
A5: 803 | B5: Pre-market (800-1299) | C5: Quiet | D5: No major recorded crisis, default or scandal | E5: None | F5: - | G5: No episode of significant scale in the surviving record for this year. Coverage in this period is fragmentary everywhere and near-absent for much of Europe; silence is very weak evidence. | H5: 0
A6: 804 | B6: Pre-market (800-1299) | C6: Quiet | D6: No major recorded crisis, default or scandal | E6: None | F6: - | G6: No episode of significant scale in the surviving record for this year. Coverage in this period is fragmentary everywhere and near-absent for much of Europe; silence is very weak evidence. | H6: 0
A7: 805 | B7: Pre-market (800-1299) | C7: Quiet | D7: No major recorded crisis, default or scandal | E7: None | F7: - | G7: No episode of significant scale in the surviving record for this year. Coverage in this period is fragmentary everywhere and near-absent for much of Europe; silence is very weak evidence. | H7: 0
A8: 806 | B8: Pre-market (800-1299) | C8: EVENT | D8: Tang 'money famine' (qian huang) | E8: Monetary contraction | F8: China | G8: Copper coin was chronically short as the Tang economy monetised faster than the mints could supply. Coin was hoarded and melted for bronzeware, which was worth more than the coin itself. | H8: 3
A9: 807 | B9: Pre-market (800-1299) | C9: Quiet | D9: No major recorded crisis, default or scandal | E9: None | F9: - | G9: No episode of significant scale in the surviving record for this year. Coverage in this period is fragmentary everywhere and near-absent for much of Europe; silence is very weak evidence. | H9: 0
A10: 808 | B10: Pre-market (800-1299) | C10: Quiet | D10: No major recorded crisis, default or scandal | E10: None | F10: - | G10: No episode of significant scale in the surviving record for this year. Coverage in this period is fragmentary everywhere and near-absent for much of Europe; silence is very weak evidence. | H10: 0
A11: 809 | B11: Pre-market (800-1299) | C11: Quiet | D11: No major recorded crisis, default or scandal | E11: None | F11: - | G11: No episode of significant scale in the surviving record for this year. Coverage in this period is fragmentary everywhere and near-absent for much of Europe; silence is very weak evidence. | H11: 0
A12: 810 | B12: Pre-market (800-1299) | C12: Quiet | D12: No major recorded crisis, default or scandal | E12: None | F12: - | G12: No episode of significant scale in the surviving record for this year. Coverage in this period is fragmentary everywhere and near-absent for much of Europe; silence is very weak evidence. | H12: 0
A13: 811 | B13: Pre-market (800-1299) | C13: EVENT | D13: Tang bans coin hoarding; 'flying cash' emerges | E13: Monetary contraction / Milestone | F13: China | G13: The state capped private coin holdings. Merchants worked around the shortage with feiqian, remittance drafts allowing money paid in the capital to be drawn in the provinces - a functioning bill of exchange six centuries before Europe. | H13: 2
... A1228: 2026 | B1228: Modern floating-rate | C1228: EVENT | D1228: AI-CAPEX BUBBLE DEBATE (unresolved); Feb volatility episode; private credit under stress test | E1228: Suspected bubble / Ongoing | F1228: Global | G1228: As at July 2026 no crash has occurred, but the conditions are widely flagged. The cyclically adjusted P/E stood near 39.8 against a long-run average of about 17.7 and the top ten S&P 500 names exceeded a third of the index. A viral Citrini Research report on a hypothetical 2028 AI-driven crisis contributed to a sharp one-day S&P 500 fall in late February; a tariff-threat selloff hit on 20 January; ECB economists publicly warned of a likely correction. Regulators including the Bank of England ran stress tests on private credit after the 2025 failures. Smaller incidents: a $26m DeFi exploit at Truebit in January, a Europol takedown of a EUR 700m crypto fraud network in January, and a SEBI warning in July on AI deepfake executive-impersonation fraud at listed companies. | H1228: 3

Sheet Event Years Only
A1: Year | B1: Era | C1: Status | D1: Event / Episode | E1: Category | F1: Geography | G1: What Happened | H1: Severity (0-5)
A2: 806 | B2: Pre-market (800-1299) | C2: EVENT | D2: Tang 'money famine' (qian huang) | E2: Monetary contraction | F2: China | G2: Copper coin was chronically short as the Tang economy monetised faster than the mints could supply. Coin was hoarded and melted for bronzeware, which was worth more than the coin itself. | H2: 3
A3: 811 | B3: Pre-market (800-1299) | C3: EVENT | D3: Tang bans coin hoarding; 'flying cash' emerges | E3: Monetary contraction / Milestone | F3: China | G3: The state capped private coin holdings. Merchants worked around the shortage with feiqian, remittance drafts allowing money paid in the capital to be drawn in the provinces - a functioning bill of exchange six centuries before Europe. | H3: 2
A4: 845 | B4: Pre-market (800-1299) | C4: EVENT | D4: GREAT ANTI-BUDDHIST PERSECUTION - monastic wealth confiscated | E4: Sovereign expropriation | F4: China | G4: Emperor Wuzong dissolved some 4,600 monasteries, seized their land and defrocked 260,000 monks, melting bronze statuary and bells into coin to solve the copper shortage. A state seizure of the largest pool of private wealth in the empire, executed explicitly as monetary policy. | H4: 4
A5: 846 | B5: Pre-market (800-1299) | C5: EVENT | D5: Monastic credit network destroyed | E5: Credit collapse | F5: China | G5: Buddhist monasteries had been China's principal lenders, pawnbrokers and grain-storage institutions. Their dissolution removed the rural credit system. | H5: 3
A6: 861 | B6: Pre-market (800-1299) | C6: EVENT | D6: ANARCHY AT SAMARRA begins - Abbasid fiscal collapse | E6: Fiscal collapse | F6: Abbasid Caliphate | G6: After al-Mutawakkil's murder, four caliphs died in nine years while the Turkish guard demanded pay the treasury did not have. Tax revenue collapsed, the dirham was debased, and the richest state on earth became insolvent. | H6: 4
A7: 866 | B7: Pre-market (800-1299) | C7: EVENT | D7: Samarra anarchy peak; Baghdad besieged | E7: Fiscal collapse | F7: Abbasid Caliphate | G7: Rival caliphs fought over an empty treasury. Provincial governors stopped remitting revenue and began keeping it. | H7: 4
A8: 869 | B8: Pre-market (800-1299) | C8: EVENT | D8: ZANJ REBELLION begins | E8: Systemic shock | F8: Abbasid Caliphate (Iraq) | G8: A rising of enslaved East African labourers in the salt marshes of southern Iraq. It occupied the most commercially valuable region of the caliphate for fourteen years. | H8: 4
A9: 871 | B9: Pre-market (800-1299) | C9: EVENT | D9: Zanj sack Basra | E9: Systemic shock | F9: Abbasid Caliphate (Iraq) | G9: Basra was the entrepot of the Indian Ocean trade and the centre of Gulf commercial finance. Its destruction severed the caliphate's most profitable revenue stream. | H9: 4
A10: 878 | B10: Pre-market (800-1299) | C10: EVENT | D10: Zanj war; southern Iraqi agriculture ruined | E10: Systemic shock | F10: Abbasid Caliphate (Iraq) | G10: The irrigation system of the Sawad, the caliphate's tax base, was wrecked and never fully restored. | H10: 3
A11: 879 | B11: Pre-market (800-1299) | C11: EVENT | D11: Huang Chao sacks Guangzhou | E11: Systemic shock | F11: China | G11: The rebel army massacred the foreign merchant community - Arab, Persian and Jewish traders - in China's principal international port. Contemporary Arabic accounts put the dead in the tens of thousands. Maritime trade finance between China and the Gulf collapsed for a generation. | H11: 4
A12: 880 | B12: Pre-market (800-1299) | C12: EVENT | D12: Huang Chao sacks Chang'an | E12: Systemic shock | F12: China | G12: The Tang capital was destroyed. Central fiscal authority never recovered; the dynasty fell in 907. | H12: 4
A13: 883 | B13: Pre-market (800-1299) | C13: EVENT | D13: Zanj rebellion suppressed | E13: Recovery | F13: Abbasid Caliphate (Iraq) | G13: Order restored at enormous cost, but Basra's commercial primacy passed permanently to Egypt and the Red Sea route. | H13: 3
... A290: 2026 | B290: Modern floating-rate | C290: EVENT | D290: AI-CAPEX BUBBLE DEBATE (unresolved); Feb volatility episode; private credit under stress test | E290: Suspected bubble / Ongoing | F290: Global | G290: As at July 2026 no crash has occurred, but the conditions are widely flagged. The cyclically adjusted P/E stood near 39.8 against a long-run average of about 17.7 and the top ten S&P 500 names exceeded a third of the index. A viral Citrini Research report on a hypothetical 2028 AI-driven crisis contributed to a sharp one-day S&P 500 fall in late February; a tariff-threat selloff hit on 20 January; ECB economists publicly warned of a likely correction. Regulators including the Bank of England ran stress tests on private credit after the 2025 failures. Smaller incidents: a $26m DeFi exploit at Truebit in January, a Europol takedown of a EUR 700m crypto fraud network in January, and a SEBI warning in July on AI deepfake executive-impersonation fraud at listed companies. | H290: 3

Sheet Period Summary
A1: Half-century | B1: From | C1: To | D1: Years | E1: Event Years | F1: % Event Years | G1: Total Severity | H1: Peak Severity
A2: 800-849 | B2: 800 | C2: 849 | D2: =C2-B2+1 -> 50 | E2: =_xlfn.COUNTIFS('Year by Year'!$A$2:$A$1228,">="&B2,'Year by Year'!$A$2:$A$1228,"<="&C2,'Year by Year'!$H$2:$H$1228,">0") -> 4 | F2: =_xlfn.IFERROR(E2/D2,0) -> 0.08 | G2: =_xlfn.SUMIFS('Year by Year'!$H$2:$H$1228,'Year by Year'!$A$2:$A$1228,">="&B2,'Year by Year'!$A$2:$A$1228,"<="&C2) -> 12 | H2: =_xlfn.MAXIFS('Year by Year'!$H$2:$H$1228,'Year by Year'!$A$2:$A$1228,">="&B2,'Year by Year'!$A$2:$A$1228,"<="&C2) -> 4
A3: 850-899 | B3: 850 | C3: 899 | D3: =C3-B3+1 -> 50 | E3: =_xlfn.COUNTIFS('Year by Year'!$A$2:$A$1228,">="&B3,'Year by Year'!$A$2:$A$1228,"<="&C3,'Year by Year'!$H$2:$H$1228,">0") -> 8 | F3: =_xlfn.IFERROR(E3/D3,0) -> 0.16 | G3: =_xlfn.SUMIFS('Year by Year'!$H$2:$H$1228,'Year by Year'!$A$2:$A$1228,">="&B3,'Year by Year'!$A$2:$A$1228,"<="&C3) -> 30 | H3: =_xlfn.MAXIFS('Year by Year'!$H$2:$H$1228,'Year by Year'!$A$2:$A$1228,">="&B3,'Year by Year'!$A$2:$A$1228,"<="&C3) -> 4
A4: 900-949 | B4: 900 | C4: 949 | D4: =C4-B4+1 -> 50 | E4: =_xlfn.COUNTIFS('Year by Year'!$A$2:$A$1228,">="&B4,'Year by Year'!$A$2:$A$1228,"<="&C4,'Year by Year'!$H$2:$H$1228,">0") -> 5 | F4: =_xlfn.IFERROR(E4/D4,0) -> 0.1 | G4: =_xlfn.SUMIFS('Year by Year'!$H$2:$H$1228,'Year by Year'!$A$2:$A$1228,">="&B4,'Year by Year'!$A$2:$A$1228,"<="&C4) -> 16 | H4: =_xlfn.MAXIFS('Year by Year'!$H$2:$H$1228,'Year by Year'!$A$2:$A$1228,">="&B4,'Year by Year'!$A$2:$A$1228,"<="&C4) -> 4
A5: 950-999 | B5: 950 | C5: 999 | D5: =C5-B5+1 -> 50 | E5: =_xlfn.COUNTIFS('Year by Year'!$A$2:$A$1228,">="&B5,'Year by Year'!$A$2:$A$1228,"<="&C5,'Year by Year'!$H$2:$H$1228,">0") -> 2 | F5: =_xlfn.IFERROR(E5/D5,0) -> 0.04 | G5: =_xlfn.SUMIFS('Year by Year'!$H$2:$H$1228,'Year by Year'!$A$2:$A$1228,">="&B5,'Year by Year'!$A$2:$A$1228,"<="&C5) -> 6 | H5: =_xlfn.MAXIFS('Year by Year'!$H$2:$H$1228,'Year by Year'!$A$2:$A$1228,">="&B5,'Year by Year'!$A$2:$A$1228,"<="&C5) -> 3
A6: 1000-1049 | B6: 1000 | C6: 1049 | D6: =C6-B6+1 -> 50 | E6: =_xlfn.COUNTIFS('Year by Year'!$A$2:$A$1228,">="&B6,'Year by Year'!$A$2:$A$1228,"<="&C6,'Year by Year'!$H$2:$H$1228,">0") -> 9 | F6: =_xlfn.IFERROR(E6/D6,0) -> 0.18 | G6: =_xlfn.SUMIFS('Year by Year'!$H$2:$H$1228,'Year by Year'!$A$2:$A$1228,">="&B6,'Year by Year'!$A$2:$A$1228,"<="&C6) -> 30 | H6: =_xlfn.MAXIFS('Year by Year'!$H$2:$H$1228,'Year by Year'!$A$2:$A$1228,">="&B6,'Year by Year'!$A$2:$A$1228,"<="&C6) -> 4
A7: 1050-1099 | B7: 1050 | C7: 1099 | D7: =C7-B7+1 -> 50 | E7: =_xlfn.COUNTIFS('Year by Year'!$A$2:$A$1228,">="&B7,'Year by Year'!$A$2:$A$1228,"<="&C7,'Year by Year'!$H$2:$H$1228,">0") -> 11 | F7: =_xlfn.IFERROR(E7/D7,0) -> 0.22 | G7: =_xlfn.SUMIFS('Year by Year'!$H$2:$H$1228,'Year by Year'!$A$2:$A$1228,">="&B7,'Year by Year'!$A$2:$A$1228,"<="&C7) -> 42 | H7: =_xlfn.MAXIFS('Year by Year'!$H$2:$H$1228,'Year by Year'!$A$2:$A$1228,">="&B7,'Year by Year'!$A$2:$A$1228,"<="&C7) -> 5
A8: 1100-1149 | B8: 1100 | C8: 1149 | D8: =C8-B8+1 -> 50 | E8: =_xlfn.COUNTIFS('Year by Year'!$A$2:$A$1228,">="&B8,'Year by Year'!$A$2:$A$1228,"<="&C8,'Year by Year'!$H$2:$H$1228,">0") -> 3 | F8: =_xlfn.IFERROR(E8/D8,0) -> 0.06 | G8: =_xlfn.SUMIFS('Year by Year'!$H$2:$H$1228,'Year by Year'!$A$2:$A$1228,">="&B8,'Year by Year'!$A$2:$A$1228,"<="&C8) -> 9 | H8: =_xlfn.MAXIFS('Year by Year'!$H$2:$H$1228,'Year by Year'!$A$2:$A$1228,">="&B8,'Year by Year'!$A$2:$A$1228,"<="&C8) -> 3
A9: 1150-1199 | B9: 1150 | C9: 1199 | D9: =C9-B9+1 -> 50 | E9: =_xlfn.COUNTIFS('Year by Year'!$A$2:$A$1228,">="&B9,'Year by Year'!$A$2:$A$1228,"<="&C9,'Year by Year'!$H$2:$H$1228,">0") -> 6 | F9: =_xlfn.IFERROR(E9/D9,0) -> 0.12 | G9: =_xlfn.SUMIFS('Year by Year'!$H$2:$H$1228,'Year by Year'!$A$2:$A$1228,">="&B9,'Year by Year'!$A$2:$A$1228,"<="&C9) -> 18 | H9: =_xlfn.MAXIFS('Year by Year'!$H$2:$H$1228,'Year by Year'!$A$2:$A$1228,">="&B9,'Year by Year'!$A$2:$A$1228,"<="&C9) -> 4
A10: 1200-1249 | B10: 1200 | C10: 1249 | D10: =C10-B10+1 -> 50 | E10: =_xlfn.COUNTIFS('Year by Year'!$A$2:$A$1228,">="&B10,'Year by Year'!$A$2:$A$1228,"<="&C10,'Year by Year'!$H$2:$H$1228,">0") -> 8 | F10: =_xlfn.IFERROR(E10/D10,0) -> 0.16 | G10: =_xlfn.SUMIFS('Year by Year'!$H$2:$H$1228,'Year by Year'!$A$2:$A$1228,">="&B10,'Year by Year'!$A$2:$A$1228,"<="&C10) -> 27 | H10: =_xlfn.MAXIFS('Year by Year'!$H$2:$H$1228,'Year by Year'!$A$2:$A$1228,">="&B10,'Year by Year'!$A$2:$A$1228,"<="&C10) -> 5
A11: 1250-1299 | B11: 1250 | C11: 1299 | D11: =C11-B11+1 -> 50 | E11: =_xlfn.COUNTIFS('Year by Year'!$A$2:$A$1228,">="&B11,'Year by Year'!$A$2:$A$1228,"<="&C11,'Year by Year'!$H$2:$H$1228,">0") -> 18 | F11: =_xlfn.IFERROR(E11/D11,0) -> 0.36 | G11: =_xlfn.SUMIFS('Year by Year'!$H$2:$H$1228,'Year by Year'!$A$2:$A$1228,">="&B11,'Year by Year'!$A$2:$A$1228,"<="&C11) -> 54 | H11: =_xlfn.MAXIFS('Year by Year'!$H$2:$H$1228,'Year by Year'!$A$2:$A$1228,">="&B11,'Year by Year'!$A$2:$A$1228,"<="&C11) -> 5
A12: 1300-1349 | B12: 1300 | C12: 1349 | D12: =C12-B12+1 -> 50 | E12: =_xlfn.COUNTIFS('Year by Year'!$A$2:$A$1228,">="&B12,'Year by Year'!$A$2:$A$1228,"<="&C12,'Year by Year'!$H$2:$H$1228,">0") -> 19 | F12: =_xlfn.IFERROR(E12/D12,0) -> 0.38 | G12: =_xlfn.SUMIFS('Year by Year'!$H$2:$H$1228,'Year by Year'!$A$2:$A$1228,">="&B12,'Year by Year'!$A$2:$A$1228,"<="&C12) -> 66 | H12: =_xlfn.MAXIFS('Year by Year'!$H$2:$H$1228,'Year by Year'!$A$2:$A$1228,">="&B12,'Year by Year'!$A$2:$A$1228,"<="&C12) -> 5
A13: 1350-1399 | B13: 1350 | C13: 1399 | D13: =C13-B13+1 -> 50 | E13: =_xlfn.COUNTIFS('Year by Year'!$A$2:$A$1228,">="&B13,'Year by Year'!$A$2:$A$1228,"<="&C13,'Year by Year'!$H$2:$H$1228,">0") -> 8 | F13: =_xlfn.IFERROR(E13/D13,0) -> 0.16 | G13: =_xlfn.SUMIFS('Year by Year'!$H$2:$H$1228,'Year by Year'!$A$2:$A$1228,">="&B13,'Year by Year'!$A$2:$A$1228,"<="&C13) -> 21 | H13: =_xlfn.MAXIFS('Year by Year'!$H$2:$H$1228,'Year by Year'!$A$2:$A$1228,">="&B13,'Year by Year'!$A$2:$A$1228,"<="&C13) -> 4
... A26: 2000-2026 | B26: 2000 | C26: 2026 | D26: =C26-B26+1 -> 27 | E26: =_xlfn.COUNTIFS('Year by Year'!$A$2:$A$1228,">="&B26,'Year by Year'!$A$2:$A$1228,"<="&C26,'Year by Year'!$H$2:$H$1228,">0") -> 27 | F26: =_xlfn.IFERROR(E26/D26,0) -> 1 | G26: =_xlfn.SUMIFS('Year by Year'!$H$2:$H$1228,'Year by Year'!$A$2:$A$1228,">="&B26,'Year by Year'!$A$2:$A$1228,"<="&C26) -> 110 | H26: =_xlfn.MAXIFS('Year by Year'!$H$2:$H$1228,'Year by Year'!$A$2:$A$1228,">="&B26,'Year by Year'!$A$2:$A$1228,"<="&C26) -> 5
A27: TOTAL 800-2026 | B27: 800 | C27: 2026 | D27: =SUM(D2:D26) -> 1227 | E27: =SUM(E2:E26) -> 289 | F27: =_xlfn.IFERROR(E27/D27,0) -> 0.23553382 | G27: =SUM(G2:G26) -> 966 | H27: =MAX(H2:H26) -> 5

Sheet Legend & Method
A1: TITLE | B1: Financial Crises, Bubbles, Defaults and Scandals: Year-by-Year Register, 800-2026 (1,227 years)
A3: Coverage | B3: All 1,227 years from 800 through July 2026, every year a separate row, on one consistent 0-5 severity scale. Merges three registers: 800-1299, 1300-1600 and 1601-2026.
A4: Prepared for | B4: Aman Maheshwari, Kyro Asset Management Pvt. Ltd.
A5: Cut-off | B5: 2026 events through July. 2026 is an open, unresolved year.
A6: Era column | B6: Pre-market (800-1299) | Medieval-Renaissance (1300-1600) | Joint-stock era (1601-1720) | Industrial / classical (1721-1913) | Wars & Bretton Woods (1914-1971) | Modern floating-rate (1972-2026). Filter on it to compare like with like.
A8: SEVERITY SCALE | B8: Identical to the companion registers, so all years are comparable.
A9: 0 | B9: No significant recorded event, or an institutional milestone with no loss event.
A10: 1 | B10: Local or minor.
A11: 2 | B11: Notable but contained within one institution, city or court.
A12: 3 | B12: Major national or single-market event.
A13: 4 | B13: Major multi-market or cross-border crisis.
A14: 5 | B14: Systemic; reshaped the financial system of its era.
A16: THE CENTRAL WARNING
A17: Do not read the trend naively | B17: Event frequency rises from about 15% of years before 1300 to 100% of years since 1990. Most of that slope is record survival and market coverage, not risk. Before 1300 we have chronicles; after 1900 we have regulators, exchanges and newspapers. The register measures what was written down at least as much as what occurred.
A18: What the trend does show | B18: Two things are real. First, coverage: from roughly 1600 onward there are tradeable financial assets, so a whole class of event - the bubble - becomes possible for the first time. Second, coupling: the share of events rated 4 or 5 that spread across borders rises sharply after 1850 and again after 1971.
A20: THE ONE PATTERN THAT HOLDS
A21: Sovereign concentration | B21: The single most repeated failure in 1,227 years is a lender with concentrated exposure to a borrower who cannot be compelled to pay. The Riccardi of Lucca on Edward I (1294). The Bonsignori of Siena (1298). The Peruzzi and Bardi on Edward III (1343-46). The Fuggers on Philip II (1557). The Genoese on Philip II again (1575, 1596). Barings on Argentina (1890). The 1982 syndicate on Mexico. Six centuries of identical obituaries.
A22: Collateral you did not verify | B22: The second recurring form: De Angelis and the salad oil tanks (1963), Bre-X and the salted cores (1997), Madoff's statements (2008), Wirecard's Philippine escrow (2020), Tricolor and First Brands and their double-pledged receivables (2025). The instrument changes; the failure to physically confirm the asset does not.
A23: Debt relief by fiat | B23: Japan's tokusei edicts (1297, 1441) and the York bond-burning (1190) show the same result each time: cancelling debt destroys the credit supply it was meant to restore.
A25: METHOD & CAVEATS
A26: Quiet years | B26: A zero-severity year means the surviving record is silent, not that the year was stable. This caveat is severe before 1300, serious before 1500, and mild after 1800.
A27: Geographic bias | B27: Coverage of Europe is denser than the Islamic world, China, India or Japan throughout, and that gap widens the further back you go. The non-Western entries included here - Tughlaq's token coinage, the Yuan and Jin and Ming paper collapses, the Shidda al-Uzma, Gaykhatu's chao, the tokusei edicts - are the well-documented survivors, not the full set.
A28: Figures | B28: Pre-20th-century amounts are not inflation-adjusted and not reliably convertible across regions. Post-2024 figures are as reported and may be revised.
A29: Not included by design | B29: Ordinary recessions, routine bear markets, and normal enforcement actions. The bar is a mania, panic, crash, systemic banking failure, sovereign default, hyperinflation, debasement or major fraud.
A31: SOURCES | B31: Spufford; Hendy and Morrisson; Goitein; Kennedy; von Glahn; Lopez; Kaeuper; Villani; de Roover; Hunt; Braudel; Cipolla; Munro; Kindleberger & Aliber; Reinhart & Rogoff; Galbraith; Chancellor; Bagehot; Bank of England and BIS historical series; NBER; SEC, FCA, SFO and SEBI enforcement records; contemporary reporting for 2020-2026.
